gabes_firstpackage/__init__.py
gabes_firstpackage/functions.py
gabes_firstpackage/mlp_momentum.py
gabes_firstpackage-1.2.1.dist-info/LICENSE.txt
gabes_firstpackage-1.2.1.dist-info/METADATA
gabes_firstpackage-1.2.1.dist-info/WHEEL
gabes_firstpackage-1.2.1.dist-info/top_level.txt
gabes_firstpackage-1.2.1.dist-info/RECORD
