Metadata-Version: 2.1
Name: gabes_firstpackage
Version: 1.2.1
Summary: My first Multilayer Perceptron and package distribution.
Author-email: Gabriel Ribeiro <gabrielc.ribeiro@hotmail.com>
Project-URL: Homepage, https://github.com/gabrielribcesario/gabes_firstpackage
Classifier: Programming Language :: Python :: 3
Classifier: License :: OSI Approved :: MIT License
Classifier: Operating System :: OS Independent
Requires-Python: >=3.9
License-File: LICENSE.txt
Requires-Dist: numpy
Requires-Dist: scikit-learn
